nonebot_plugin_lua/__init__.py
nonebot_plugin_lua/config.py
nonebot_plugin_lua/lua_config.py
nonebot_plugin_lua/lua_plugins.py
nonebot_plugin_lua/patch_bot.py
nonebot_plugin_lua/utils.py
nonebot_plugin_lua-0.0.1.dev2.dist-info/METADATA
nonebot_plugin_lua-0.0.1.dev2.dist-info/WHEEL
nonebot_plugin_lua-0.0.1.dev2.dist-info/top_level.txt
nonebot_plugin_lua-0.0.1.dev2.dist-info/RECORD
