Metadata-Version: 2.1
Name: nonebot-plugin-lua
Version: 0.0.1.dev2
Summary: A lua plugin for nonebot2
Home-page: https://github.com/synodriver/nonebot_plugin_lua
Author: synodriver
Author-email: diguohuangjiajinweijun@gmail.com
License: GPLv3
Keywords: nonebot,lua
Classifier: Framework :: AsyncIO
Classifier: Operating System :: OS Independent
Classifier: License :: OSI Approved :: GNU General Public License v3 (GPLv3)
Classifier: Programming Language :: Python
Classifier: Programming Language :: Python :: 3.7
Classifier: Programming Language :: Python :: 3.8
Classifier: Programming Language :: Python :: 3.9
Classifier: Programming Language :: Python :: 3.10
Classifier: Programming Language :: Python :: 3.11
Classifier: Programming Language :: Python :: Implementation :: CPython
Requires-Python: >=3.7
Requires-Dist: lupa
Requires-Dist: nonebot2
Requires-Dist: nonebot-adapter-onebot
